LICENSE.txt
MANIFEST.in
README.txt
motw
setup.py
PyMOTW/__init__.py
PyMOTW/cc-by-nc-sa.png
PyMOTW/feed.png
PyMOTW/mail.png
PyMOTW.egg-info/PKG-INFO
PyMOTW.egg-info/SOURCES.txt
PyMOTW.egg-info/dependency_links.txt
PyMOTW.egg-info/not-zip-safe
PyMOTW.egg-info/top_level.txt
PyMOTW/BaseHTTPServer/BaseHTTPServer_GET.py
PyMOTW/BaseHTTPServer/BaseHTTPServer_POST.py
PyMOTW/BaseHTTPServer/BaseHTTPServer_errors.py
PyMOTW/BaseHTTPServer/BaseHTTPServer_send_header.py
PyMOTW/BaseHTTPServer/BaseHTTPServer_threads.py
PyMOTW/BaseHTTPServer/__init__.py
PyMOTW/ConfigParser/ConfigParser_allow_no_value.py
PyMOTW/ConfigParser/ConfigParser_defaults.py
PyMOTW/ConfigParser/ConfigParser_has_option.py
PyMOTW/ConfigParser/ConfigParser_has_section.py
PyMOTW/ConfigParser/ConfigParser_interpolation.py
PyMOTW/ConfigParser/ConfigParser_interpolation_defaults.py
PyMOTW/ConfigParser/ConfigParser_interpolation_error.py
PyMOTW/ConfigParser/ConfigParser_interpolation_recursion.py
PyMOTW/ConfigParser/ConfigParser_populate.py
PyMOTW/ConfigParser/ConfigParser_read.py
PyMOTW/ConfigParser/ConfigParser_read_many.py
PyMOTW/ConfigParser/ConfigParser_remove.py
PyMOTW/ConfigParser/ConfigParser_structure.py
PyMOTW/ConfigParser/ConfigParser_unicode.py
PyMOTW/ConfigParser/ConfigParser_value_types.py
PyMOTW/ConfigParser/ConfigParser_write.py
PyMOTW/ConfigParser/__init__.py
PyMOTW/ConfigParser/configparser_example.py
PyMOTW/Cookie/Cookie_Morsel.py
PyMOTW/Cookie/Cookie_coded_value.py
PyMOTW/Cookie/Cookie_js_output.py
PyMOTW/Cookie/Cookie_parse.py
PyMOTW/Cookie/Cookie_setheaders.py
PyMOTW/Cookie/__init__.py
PyMOTW/Queue/Queue_fifo.py
PyMOTW/Queue/Queue_lifo.py
PyMOTW/Queue/Queue_priority.py
PyMOTW/Queue/__init__.py
PyMOTW/Queue/feedparser.py
PyMOTW/Queue/fetch_podcasts.py
PyMOTW/SimpleXMLRPCServer/SimpleXMLRPCServer_alternate_name.py
PyMOTW/SimpleXMLRPCServer/SimpleXMLRPCServer_alternate_name_client.py
PyMOTW/SimpleXMLRPCServer/SimpleXMLRPCServer_arbitrary_name.py
PyMOTW/SimpleXMLRPCServer/SimpleXMLRPCServer_arbitrary_name_client.py
PyMOTW/SimpleXMLRPCServer/SimpleXMLRPCServer_dotted_name.py
PyMOTW/SimpleXMLRPCServer/SimpleXMLRPCServer_dotted_name_client.py
